termslime/.gitignore
termslime/__main__.py
termslime-0.2.1.dist-info/entry_points.txt
termslime-0.2.1.dist-info/LICENSE
termslime-0.2.1.dist-info/METADATA
termslime-0.2.1.dist-info/WHEEL
termslime-0.2.1.dist-info/RECORD
